ja_cvu_normalizer/__init__.py
ja_cvu_normalizer/ja_cvu_normalizer.py
ja_cvu_normalizer/reader.py
ja_cvu_normalizer/resource/ISO-2022-JP.txt
ja_cvu_normalizer/resource/__init__.py
ja_cvu_normalizer-0.2.10.dist-info/METADATA
ja_cvu_normalizer-0.2.10.dist-info/WHEEL
ja_cvu_normalizer-0.2.10.dist-info/RECORD
