Metadata-Version: 2.3
Name: ja_cvu_normalizer
Version: 0.2.10
Summary: 異体字正規化モジュール
Project-URL: Homepage, https://github.com/ekurerice/ja_cvu_normalizer
Project-URL: Issues, https://github.com/ekurerice/ja_cvu_normalizer/issues
Author-email: ekurerice <alexandria.rindybell@gmail.com>
License: MIT License
Keywords: Japanese,Unicode,normalizer
Classifier: License :: OSI Approved :: MIT License
Classifier: Operating System :: OS Independent
Classifier: Programming Language :: Python :: 3
Requires-Python: >=3.6
